strpdatetime.py
strpdatetime-0.3.0.dist-info/LICENSE
strpdatetime-0.3.0.dist-info/METADATA
strpdatetime-0.3.0.dist-info/WHEEL
strpdatetime-0.3.0.dist-info/RECORD
