Metadata-Version: 2.1
Name: strpdatetime
Version: 0.3.0
Summary: Parse strings into Python datetime objects; extends Python's datetime.strptime() with additional features.
License: Python Software Foundation License
Author: Rhet Turnbull
Author-email: rturnbull+git@gmail.com
Requires-Python: >=3.9,<3.13
Classifier: License :: Other/Proprietary License
Classifier: Programming Language :: Python :: 3
Classifier: Programming Language :: Python :: 3.9
Classifier: Programming Language :: Python :: 3.10
Classifier: Programming Language :: Python :: 3.11
Classifier: Programming Language :: Python :: 3.12
Requires-Dist: textX (>=4.0.1,<5.0.0)
